<?xml version="1.0" encoding="utf-8"?>
<contentList>
  -- MISC --

  <content contentuid="h791d7252g22e8g4a61gaf65g9a2324ccdf6e" version="1">Helm of Sel没ne</content> 
  <content contentuid="h884099fag346fg4b08ga0cbg62bf9b62929a" version="1">And they smote the enemies of the faith with a righteous fury, for they knew they were doing Her work.</content>
  <content contentuid="hae827209gfe8bg48c0g94dagfe4dc2bbb8c7" version="1">Radiant Dive</content> 
  <content contentuid="ha0bdcae1g8b12g498eg8541g0588ade98a3f" version="1">Sel没ne's Wrath</content>
  <content contentuid="h9095feacg1e6fg4a0agb910g5a62322fa48c" version="1">Sel没ne's fury is as great as her mercy. Become an aspect of Sel没ne, strengthening all abilities.</content>
  <content contentuid="h35d15d21g4561g437fga568gc574395eac24" version="1">Gith Champion's WardPlate</content>
  <content contentuid="h62a85c9cge2e1g4ebbgbad6gb15829f2a158" version="1">An artisan chestpiece for the chosen champion of Gith. Offers unparalleled protection aginst foes of the regime.</content>
  <content contentuid="h02bf92a9gd736g4cbcga907gb4924152fb5b" version="1">Gith Step</content>
  <content contentuid="hce6c2b0cg6dc5g45fag9119gbe94f4b24597" version="1">Gith's chosen are akin to a tempest: The only mark of their presence are the shattered remains they leave behind.</content>
  <content contentuid="hb0a3666age87eg4bfcgacbcg2e21ae506127" version="1">Karlach's Drip</content>
  <content contentuid="ha3a045e2g7331g4e9dgaa77gc2939bf34fd7" version="1">This girl doesn't have a fuck to give to you.</content>
  <content contentuid="h33d86e83g0517g4eacgb01fgbdc3d7e95029" version="1">Rage of Avernus</content>
  <content contentuid="hd5dd37bbgc5dbg4b62g83deg5a74a2745771" version="1">Karlach unleases her infernal might. Let's party!</content>
  <content contentuid="h45058278g39b3g4ef6gb53dg8c4629ee23d9" version="1">Heat Generation</content>
  <content contentuid="h68538eb1g37ffg4071gaa63g328d457371a0" version="1">Generates Heat every turn.</content>

  -- WEAPONS --

  <content contentuid="h98f492d8g393bg48adg9c7fgced38b9416c3" version="1">Sam's Misread Charm Necklace</content> 
  <content contentuid="h996611a6g19ecg46bcgbf0fg3c714e75483d" version="1">When the Dungeon Master didn't know what the "Charm Person" spell did....</content>
  <content contentuid="h1995f182g101cg4a74g9cddgdbf037d09f79" version="1">Witcher's Silver Longsword</content> 
  <content contentuid="h88756d94g5cfbg42f2g9851g627b64419034" version="1">Forged with silver from a falling star, a silver blade is an indispensable part of a witcher's monster slaying arsenal.</content>
  <content contentuid="h393cc8f0g2393g4b05g9bc9g871f95dbfb74" version="1">Monster Slayer Longsword</content> 
  <content contentuid="h7df25785g34f5g4076gbfccg9ab50ba4d8de" version="1">The blade reverberates with the muted cries of beasts that fell to its edge.</content>
  <content contentuid="h35bdfaefg7245g4795g92c2g6cc7cd296c91" version="1">Cunning Hand Crossbow</content> 
  <content contentuid="hf4f5ceb3gba8bg4bdbga757ge44aaecc05d4" version="1">Restored from oblivion, the bow sings with eagerness to leap into battle.</content>
  <content contentuid="h6d586c1cg863bg4c8egb470g10b6012cbc04" version="1">Dimeritium Longsword</content> 
  <content contentuid="ha13d3a2egf991g4c03gb35cg0d25a840c5d0" version="1">Terranova cried out, struggled, bent over and retched and Geralt realised what the handcuffs were made of. It was an alloy of iron and dimeritium, a rare metal characterised by its inhibition of magical powers.</content>
  <content contentuid="h9ecf974fga795g4e77gbab5gfa74574196c5" version="1">Witcher's Hand Crossbow</content> 
  <content contentuid="hd53da196g0bccg4587gbc30g8a6c609d0322" version="1">Well then, I seem to recall a rather pleasant little restaurant not far from here. Care to see if it's still standing?.</content>

  -- WITCHER CLASS -- 

  <content contentuid="h9893eeaagea76g4a95g950ag9ee5480f6be5" version="1">Witcher</content> 
  <content contentuid="h7165401ag0611g462ag8e13g94bf728bdd89" version="1">Born of mutation and martial training, witchers are mysterious master hunters of beasts, spoken about in hushed tones by the common folk.</content>
  <content contentuid="hc7ca3767gae03g4c6agb8b9gdc676bfb7713" version="1">Mutant Enhancements</content> 
  <content contentuid="h0c1bca67gb536g44fag8863gec36c9fd8710" version="1">The Trials have enhanced your capabilities:</content>
  <content contentuid="h20240b4ag8b16g4e8eg8879g43fcc0919943" version="1">Toxic Tolerance</content> 
  <content contentuid="h52d26518ge540g4c1ag8ca6gedbad4fa3a57" version="1">Gain Poison Resistance and Immunity to various debilitating potion effects (Poisoned, Lethargy).</content>
  <content contentuid="h71b1e7c9gbeb1g4a01ga385gf7f4f0e11a8c" version="1">Prone Execution</content> 
  <content contentuid="h9eca98c1ga661g48e4gb340ge5af7bd40a0b" version="1">Chance to instantly execute Prone enemies. Increased by Proficiency Bonus</content> 
  <content contentuid="h70a1b451gee3dg4ef9g8649ge8f65cb770e1" version="1">Witcher's Focus</content> 
  <content contentuid="hfe1defe8gb391g4223g94b9gb6dd1c65352d" version="1">Enter a state of utter focus. Able to parry incoming attacks and deal felling blows.</content> 
  <content contentuid="hd7de5597g744bg4a9bg8f33g992389177ab9" version="1">Crippling Strikes</content> 
  <content contentuid="h0fcc9a98ga99cg41efg868bg912dd578093f" version="1">Attacks have a High Chance to apply Bleed on targets.</content> 
  <content contentuid="ha7144b83g52d6g4ae2gafaag3ff7d0432084" version="1">Rend</content> 
  <content contentuid="h051efc4dg344cg41c9ga16cgdc08bfed00e1" version="1">A concentrated strike that consumes all charges of Focus to deal monstrous damage.</content> 

  // Elixir Bonus
  <content contentuid="h269331a4g5124g491cg8e4bg6cb3e462f2ec" version="1">Specialization: Elixir Bonus</content> 
  <content contentuid="ha6a8e7d0ge7dcg475agbbb8g047045e32e9d" version="1">Gain one of the following additional effects while under the influence of an Elixir.</content>
  <content contentuid="h382cc05fg3a59g45efgbd4ag9177bb738d37" version="1">Lethal Precision</content> 
  <content contentuid="h669c4a2cgdf3dg4e1bg9171gb76ea9557a68" version="1">+2 to Attack Rolls with Proficient weapons.</content>
  <content contentuid="hdadb4cb8g1db1g4e32gb3c7g51baf5a9adc8" version="1">Sign Intensity</content> 
  <content contentuid="h6aa39bf5g51feg478bgaba9ga37665b4993a" version="1">+2 to Spell Save DC.</content>
  //Witcher Expertise
  <content contentuid="hd71570f8g8b66g4c47g9983gf07e8fc6e63b" version="1">Witcher Expertise</content> 
  <content contentuid="h16d6d37cge75cg40b4g9695g86bbecf9108f" version="1">Gain Expertise and Proficiency in two of the following Skills.</content>
  <content contentuid="h062748e7g6ae1g40b0ga842g215a9154e517" version="1">Witcher Expertise: Arcana</content> 
  <content contentuid="h1d227bdcg2bbag4e44gbe9fgb1a6aae0d8fd" version="1">Proficiency and Expertise in Arcana.</content>
  <content contentuid="h71a4a6f5g2547g4c9dg8c7fgec017127b738" version="1">Witcher Expertise: Investigation</content> 
  <content contentuid="h80d2aa2agdd46g4399g98d6gb37e1208ebff" version="1">Proficiency and Expertise in Investigation.</content>
  <content contentuid="h0db1edfbg5b14g4ba5gb657g045087d12890" version="1">Witcher Expertise: Nature</content> 
  <content contentuid="h099b5310gf994g4ec8gaac4gdc4626b4dee2" version="1">Proficiency and Expertise in Nature.</content>
  <content contentuid="h07431404g31c1g49e3gbb02ga5a313f15508" version="1">Witcher Expertise: Medicine</content> 
  <content contentuid="h2f031d46g1cb9g41deg8aa2g638ef03c66e1" version="1">Proficiency and Expertise in Medicine.</content>
  //Mutant Enhancements
  <content contentuid="h9b120b98g6bc6g4f34ga45ag2373ed5fdeec" version="1">Aggravating Wounds</content> 
  <content contentuid="ha3bda703gfbe3g440ega5d6gd43c0c1bb076" version="1">Deal 1d8 additional damage to Bleeding and Poisoned targets.</content>
  <content contentuid="he82887bdg2a6bg4c04gb76fg750556784fb9" version="1">Sunder Armor</content> 
  <content contentuid="hbf70b199gc305g4073ga272gce93a848d635" version="1">Your weapon attacks apply Sunder Armor for 2 turns.</content>
  <content contentuid="hee62585fg70cdg4309g9fd7gd7e0be22e34f" version="1">AC reduced by 1.</content>
  <content contentuid="h9d7c7777g6f14g49c7gafafged9f3734fd70" version="1">Persuasive Presence</content> 
  <content contentuid="h0a49a7eegec8cg4b5ega794g64ea88a686d9" version="1">Learn the Charm Person spell.</content>
  <content contentuid="h2049a99cg617cg4a41ga345geb65c09e01b2" version="1">Intimidating Presence</content> 
  <content contentuid="hcd301082g5c66g41acgbd19g2ac8d58fd4b5" version="1">Learn the Thaumaturgy spell.</content>
  <content contentuid="h49fed922gb767g4b63g945ag04bc49424621" version="1">Maiming Strike</content> 
  <content contentuid="h857f534ege331g40bega55agc334d0032cab" version="1">Your ranged weapon attacks have a high chance to apply Crippled.</content>
  <content contentuid="h6216895bgcfd3g4777g9366gd65ef6c25f26" version="1">Melt Armor</content> 
  <content contentuid="h9a2ea0d2gbbd5g44f8g8210gb84abb04afa7" version="1">Enhanced Movement</content> 
  <content contentuid="h8e795467ga99bg4f26gaf8dg5570dc77808f" version="1">+3m movement speed</content> 
  <content contentuid="hb0b39cbdg8cd3g44c6g8e86gd1eff5087383" version="1">Enhanced Reflexes</content> 
  <content contentuid="hfc11c512gc3d2g4299ga26bg64a00c63d0c3" version="1">+2 Initiative</content>
  <content contentuid="h38c74cacg9241g4fddgb8beg535428cf26d0" version="1">Intimidating Presence</content> 
  <content contentuid="hfe0385cdgc21ag4b23ga9ddg2150fd3f5fd9" version="1">Gain Proficiency and Expertise in Intimidation.</content>
  <content contentuid="h6fda31ceg4eb7g4864g91f9g7ae86792622d" version="1">Iron Flesh</content> 
  <content contentuid="h5763cf6eg81b5g471fgb70bg9673bb19283c" version="1">Take less damage from all sources equal to your Constitution modifier.</content>
  <content contentuid="hf89f2747gca4dg4ed4gaffbg67e8861fb6b1" version="1">Unbreakable Mind</content> 
  <content contentuid="h3a20c4begd949g4c4dg90d8g332fd4e72854" version="1">Advantage on Constitution and Wisdom Saving Throws.</content>
  <content contentuid="hbff5d6d4gc89dg41f0g8c2eg99b4ab6bc59f" version="1">Murderous Surge</content> 
  <content contentuid="h27d5916fg4305g40a8g8eb3g7fea4df0ead7" version="1">Once per turn, recover 6m movement speed on kills.</content>
  <content contentuid="h48f3283fg93f1g44b7gace4g4d549f9c8aba" version="1">+6m movement speed.</content>

  -- SIGNS --

  <content contentuid="h61435b3egf9fbg4251g8eafg24b94b5406f9" version="1">Witcher Signs I</content> 
  <content contentuid="h443ff662g423cg4436gb1e3gbc37874f8111" version="1">Unlocks the basic form of Witcher signs</content>
  <content contentuid="h4f19322cg4232g47dfga70fge828647d9b41" version="1">Witcher Signs II</content> 
  <content contentuid="hc99f78e6g0349g4a26gb006g3d799ba4fa99" version="1">Unlocks the improved form of Witcher signs</content>
  <content contentuid="h83d427d2g282bg448bga7d2gf057813a706e" version="1">Witcher Signs III</content> 
  <content contentuid="h3c4ab1d9ga001g4f40g9615g71c6297eefd3" version="1">Unlocks the final form of Witcher signs</content>
  <content contentuid="h38223a72g2cdfg45c2ga952g8eb3d216ed57" version="1">Aard</content> 
  <content contentuid="hc917f757ge2d3g4236g8f5bg14aefa140abc" version="1">A cone of concussive force explodes from your palm, throwing opponents back.</content>
  <content contentuid="hdd9f7ea3gd1e5g4467g9152gf0274feffdbe" version="1">Aard:Alt</content> 
  <content contentuid="hf06aaa8fg25d3g475bga322g5b7dd0fa7a25" version="1">Alternate:You unleash a weaker wave of force around yourself, throwing opponents back.</content>
  <content contentuid="h3dfdfb66gcb9ag42f8g9618ge82293589c7b" version="1">Igni</content> 
  <content contentuid="h2a7538edg1a17g4c84g9239g1346996c0797" version="1">A cone of searing flame shoots from your fingers, stinging nearby opponents</content>
  <content contentuid="h3ac9d4c5g706cg489bgaf74g8112a7e29e04" version="1">Igni:Alt</content> 
  <content contentuid="hf51475e1g4de7g436cgaf8cgefc2658c4c3f" version="1">Alternate:A concentrated beam of fire shoots from your fingers, scorching targets further away</content>
  <content contentuid="h087cdc2bg6b86g4748gb793g37246d45b067" version="1">Quen</content> 
  <content contentuid="hdfa95f30gb7b6g4b1bg863ag9e8800cb987e" version="1">A protective shield envelops you, absorbing incoming damage.</content>
  <content contentuid="h382d9f84g50fdg47c6gbc5dg8c819660d331" version="1">Quen:Alt</content> 
  <content contentuid="h04286783g538fg4243ga909g7b290dcb0c2c" version="1">Alternate:A stronger shield takes your full effort to create, shielding and healing you for incoming damage</content>
  <content contentuid="ha53a0850gb2eag4496g802dgce7b9c204737" version="1">Axii</content> 
  <content contentuid="h3d9c0a7cgcb76g4df1g922eg3e6f0afd2ef7" version="1">Stuns your target.</content>
  <content contentuid="h524cf6fegac9dg411bgb85fga6b702286c94" version="1">Axii:Alt</content> 
  <content contentuid="h6e7abcc7g3795g4d86gbd1agd4d8bcdb28b1" version="1">[EASIER SAVING THROW]Alternate: Dominates an enemy to fight for you.</content>
  <content contentuid="ha9b0b436ga467g47abgbeb4gaeb8b3e9c728" version="1">Yrden</content> 
  <content contentuid="had0ae984g55cdg4999g9ee6gdf5aa75782b7" version="1">Creates a ward on the ground before you that slowing enemies that wander in its proximity</content>
  <content contentuid="hacbe188fgcf5cg4f2fg880eg493df4337c85" version="1">Yrden Aura</content> 
  <content contentuid="hda40bb61g0c19g4101gb306gceaf213c582f" version="1">Enemies within the aura are Slowed and Revealed</content>
  <content contentuid="hda40bb61g0c19g4101gb306gceaf213c582f" version="1">Slowed and Revealed</content>
  <content contentuid="h70c6a837g93a1g490bgba88g26c19b35f3e8" version="1">Yrden:Alt</content> 
  <content contentuid="hc9c43271gf9dbg4c12ga67ege85467bf39ae" version="1">Alternate:Creates a damaging ward on the that deals Lightning damage to enemies in the area</content>
  <content contentuid="hacca9127gbbb9g42e1g8bd9g4109ee2e2557" version="1">Yrden:Alt Aura</content> 
  <content contentuid="h5fc1afa6g9d10g4589g8d33g2df56622582f" version="1">Take Lightning damage at the start of every turn</content>
  <content contentuid="h04f56fa6g7a77g4bb7gba9eg7a066d39bdc4" version="1">Heliotrope</content> 
  <content contentuid="hbff30102ge075g4751gbf1dg7d9cf23faaf3" version="1">Gain an Action and Bonus Action.</content>
  <content contentuid="hf22859abg3ca6g44a2g9ff0g1ab0c70fb0ba" version="1">BALANCED Heliotrope</content> 
  <content contentuid="h3236b7d5g077bg42e3g994agfe03a7ea2cad" version="1">Gain an Action and Bonus Action. Enemies are fucked.</content>
  <content contentuid="h8574d051g4a17g4c9cga6c1gd56351cd6a20" version="1">BALANCED Heliotrope Aura</content> 
  <content contentuid="h601ae09cgac07g4540g9e8bg3c426c424245" version="1">You're fucked.</content>
  <content contentuid="h4cefac30g2a61g43e3g8655g7d0877deb1c3" version="1">Quen:Shield</content> 
  <content contentuid="h32374a92gd34dg4e3agb9e6g890a1ae23ed7" version="1">Gain Temporary HP. Enemy attacks release a retaliating blast that deals Force damage</content>
  <content contentuid="hc64ae53eg99deg41a2gb8ebge08234d23be7" version="1">Quen:Alt Enhanced Shield</content> 
  <content contentuid="ha3f881fcg14cbg41f0g897bga9d765895dc4" version="1">Gain Effects of Quen Aura. Gain additional Temporary HP, and enemy attacks heal you.</content>
</contentList>